confluent_kafka-stubs/__init__.pyi
confluent_kafka-stubs/cimpl.pyi
confluent_kafka_stubs-0.0.3.dist-info/LICENSE
confluent_kafka_stubs-0.0.3.dist-info/METADATA
confluent_kafka_stubs-0.0.3.dist-info/WHEEL
confluent_kafka_stubs-0.0.3.dist-info/RECORD
