Metadata-Version: 2.1
Name: confluent-kafka-stubs
Version: 0.0.3
Summary: Stub files for confluent-kafka.
Home-page: https://gitlab.com/theepic-dev/confluent-kafka-stubs
License: Apache-2.0
Keywords: kafka,stubs,types
Author: The Epic
Author-email: theepic.dev.83@gmail.com
Requires-Python: >=3.11,<4.0
Classifier: Development Status :: 3 - Alpha
Classifier: Intended Audience :: Developers
Classifier: License :: OSI Approved :: Apache Software License
Classifier: Programming Language :: Python
Classifier: Programming Language :: Python :: 3
Classifier: Programming Language :: Python :: 3.11
Classifier: Typing :: Stubs Only
Project-URL: Repository, https://gitlab.com/theepic-dev/confluent-kafka-stubs
